trism_cv/__init__.py
trism_cv/client.py
trism_cv/inout.py
trism_cv/model.py
trism_cv/types.py
trism_cv-0.0.2.dist-info/licenses/LICENSE
trism_cv-0.0.2.dist-info/METADATA
trism_cv-0.0.2.dist-info/WHEEL
trism_cv-0.0.2.dist-info/top_level.txt
trism_cv-0.0.2.dist-info/zip-safe
trism_cv-0.0.2.dist-info/RECORD
