Metadata-Version: 2.4
Name: trism-cv
Version: 0.0.2
Summary: A lightweight and modular Python package for handling computer vision inference (image/video) with Triton Inference Server.
Home-page: https://github.com/tien-ngnvan/trism-cv
Author: Tien Nguyen Van
Author-email: tien.ngnvan@gmail.com
Maintainer: Thanh Nguyen Nhut, Minh Nguyen Ngoc, Tan Mai Nhat
License: GNU AGPL v3.0
Classifier: Intended Audience :: Developers
Classifier: Topic :: Software Development :: Build Tools
License-File: LICENSE
Requires-Dist: numpy
Requires-Dist: opencv-python
Requires-Dist: tqdm
Requires-Dist: tritonclient[all]
Requires-Dist: attrdict
Dynamic: author
Dynamic: author-email
Dynamic: classifier
Dynamic: description
Dynamic: description-content-type
Dynamic: home-page
Dynamic: license
Dynamic: license-file
Dynamic: maintainer
Dynamic: requires-dist
Dynamic: summary
